partialorder.py
setup.py
partialorder.egg-info/PKG-INFO
partialorder.egg-info/SOURCES.txt
partialorder.egg-info/dependency_links.txt
partialorder.egg-info/top_level.txt