Metadata-Version: 1.0
Name: partialorder
Version: 0.0.1421587592
Summary: Provides a partial ordering version of functools.total_ordering
Home-page: UNKNOWN
Author: Mike Lang
Author-email: mikelang3000@gmail.com
License: UNKNOWN
Platform: UNKNOWN
